pycwheel.py
pycwheel-1.0.0.dist-info/DESCRIPTION.rst
pycwheel-1.0.0.dist-info/METADATA
pycwheel-1.0.0.dist-info/RECORD
pycwheel-1.0.0.dist-info/WHEEL
pycwheel-1.0.0.dist-info/entry_points.txt
pycwheel-1.0.0.dist-info/metadata.json
pycwheel-1.0.0.dist-info/pbr.json
pycwheel-1.0.0.dist-info/top_level.txt
