Metadata-Version: 2.0
Name: pycwheel
Version: 1.0.0
Summary: Compile all py files in a wheel to pyc files
Home-page: https://github.com/grantpatten/pycwheel
Author: Grant Patten
Author-email: grant@gpatten.com
License: MIT
Keywords: pyc wheel compile
Platform: UNKNOWN
Classifier: Programming Language :: Python :: 2
Classifier: Intended Audience :: Developers
Classifier: License :: OSI Approved :: MIT License
Classifier: Topic :: Utilities
